srmap/__init__.py
srmap/actor.py
srmap/level.py
srmap/property.py
srmap/tilemap.py
srmap-0.0.2.dist-info/LICENSE
srmap-0.0.2.dist-info/METADATA
srmap-0.0.2.dist-info/WHEEL
srmap-0.0.2.dist-info/top_level.txt
srmap-0.0.2.dist-info/RECORD
