Metadata-Version: 2.1
Name: srmap
Version: 0.0.2
Summary: SpeedRunners map editing library
Home-page: https://github.com/pop4959/srmap
Author: pop4959
Author-email: pop4959@gmail.com
License: UNKNOWN
Platform: UNKNOWN
